[
    {
        "race_name": "4 Bikes Festival Cyclocross Race",
        "date": "11 Sep 2021",
        "venue": "L端tzelbach",
        "category": "Men Elite",
        "event_url": "https://dataride.uci.org/iframe/EventResults/253439?competitionId=65152&disciplineId=3",
        "winner": "MEISEN Marcel"
    },
    {
        "race_name": "4 Bikes Festival Cyclocross Race",
        "date": "11 Sep 2021",
        "venue": "L端tzelbach",
        "category": "Women Elite",
        "event_url": "https://dataride.uci.org/iframe/EventResults/253349?competitionId=65152&disciplineId=3",
        "winner": "KRAHL Judith"
    },
    {
        "race_name": "4 Bikes Festival Cyclocross Race",
        "date": "11 Sep 2021",
        "venue": "L端tzelbach",
        "category": "Men Junior",
        "event_url": "https://dataride.uci.org/iframe/EventResults/253406?competitionId=65152&disciplineId=3",
        "winner": "DE MOYER Kenay"
    },
    {
        "race_name": "4 Bikes Festival Cyclocross Race",
        "date": "11 Sep 2021",
        "venue": "L端tzelbach",
        "category": "Women Junior",
        "event_url": "https://dataride.uci.org/iframe/EventResults/253430?competitionId=65152&disciplineId=3",
        "winner": "VAN SINAEY Xaydee"
    }
]